{
    "configurations": [
        {
            "name": "Win32",
            "includePath": [
                "${workspaceFolder}",
                "C:/MinGW/lib/gcc/x86_64-w64-mingw32/8.1.0/include/c++",
                "C:/MinGW/include/*",
                "C:/MinGW/lib/gcc/x86_64-w64-mingw32/8.1.0/include"
            ],
            "defines": [
                "_DEBUG",
                "UNICODE",
                "_UNICODE"
            ],
            "intelliSenseMode": "clang-x64",
            "browse": {
                "path": [
                    "${workspaceFolder}",
                    "C:/MinGW/lib/gcc/x86_64-w64-mingw32/8.1.0/include/c++",
                    "C:/MinGW/include/*",
                    "C:/MinGW/lib/gcc/x86_64-w64-mingw32/8.1.0/include"
                ],
                "limitSymbolsToIncludedHeaders": true,
                "databaseFilename": ""
            },
            "cStandard": "c11",
            "cppStandard": "c++17"
        }
    ],
    "version": 4
}